CHANGES
LICENSE
README.txt
bootstrap.py
buildout.cfg
setup.py
docs/HISTORY.txt
docs/TODO.txt
rpatterson/__init__.py
rpatterson.mailsync.egg-info/PKG-INFO
rpatterson.mailsync.egg-info/SOURCES.txt
rpatterson.mailsync.egg-info/dependency_links.txt
rpatterson.mailsync.egg-info/entry_points.txt
rpatterson.mailsync.egg-info/namespace_packages.txt
rpatterson.mailsync.egg-info/not-zip-safe
rpatterson.mailsync.egg-info/requires.txt
rpatterson.mailsync.egg-info/top_level.txt
rpatterson/mailsync/README.txt
rpatterson/mailsync/__init__.py
rpatterson/mailsync/check.py
rpatterson/mailsync/parse.py
rpatterson/mailsync/sync.py
rpatterson/mailsync/testing.py
rpatterson/mailsync/tests.py
rpatterson/mailsync/watch.py
rpatterson/mailsync/watch.txt
site-lisp/mailsync-gnus.el