Metadata-Version: 1.0
Name: rpatterson.mailsync
Version: 0.4
Summary: Integration between mswatch, OfflineIMAP, and Gnus for realtime mail
Home-page: http://pypi.python.org/pypi/rpatterson.mailsync
Author: Ross Patterson
Author-email: me@rpatterson.net
License: GPL
Platform: UNKNOWN
Classifier: Programming Language :: Python
Classifier: Topic :: Software Development :: Libraries :: Python Modules
